cdk_fck_nat/__init__.py
cdk_fck_nat/py.typed
cdk_fck_nat/_jsii/__init__.py
cdk_fck_nat/_jsii/cdk-fck-nat@1.6.18.jsii.tgz
cdk_fck_nat-1.6.18.dist-info/LICENSE
cdk_fck_nat-1.6.18.dist-info/METADATA
cdk_fck_nat-1.6.18.dist-info/WHEEL
cdk_fck_nat-1.6.18.dist-info/top_level.txt
cdk_fck_nat-1.6.18.dist-info/RECORD
