Metadata-Version: 2.1
Name: cdk-fck-nat
Version: 1.6.18
Summary: A NAT Gateway instance construct built on the fck-nat AMI.
Home-page: https://github.com/AndrewGuenther/cdk-fck-nat.git
Author: Andrew Guenther<guenther.andrew.j@gmail.com>
License: MIT
Project-URL: Source, https://github.com/AndrewGuenther/cdk-fck-nat.git
Classifier: Intended Audience :: Developers
Classifier: Operating System :: OS Independent
Classifier: Programming Language :: JavaScript
Classifier: Programming Language :: Python :: 3 :: Only
Classifier: Programming Language :: Python :: 3.9
Classifier: Programming Language :: Python :: 3.10
Classifier: Programming Language :: Python :: 3.11
Classifier: Typing :: Typed
Classifier: Development Status :: 5 - Production/Stable
Classifier: License :: OSI Approved
Requires-Python: ~=3.9
License-File: LICENSE
Requires-Dist: aws-cdk-lib <3.0.0,>=2.122.0
Requires-Dist: constructs <11.0.0,>=10.0.5
Requires-Dist: jsii <2.0.0,>=1.115.0
Requires-Dist: publication >=0.0.3
Requires-Dist: typeguard <4.3.0,>=2.13.3
